Metadata-Version: 2.2
Name: pymathics-graph
Version: 8.0.0
Maintainer: Mathics3 Group
Maintainer-email: rb@dustyfeet.com
Classifier: Intended Audience :: Developers
Classifier: Intended Audience :: Science/Research
Classifier: License :: OSI Approved :: GNU General Public License v3 (GPLv3)
Classifier: Programming Language :: Python
Classifier: Programming Language :: Python :: 3.8
Classifier: Programming Language :: Python :: 3.9
Classifier: Programming Language :: Python :: 3.10
Classifier: Programming Language :: Python :: 3.11
Classifier: Programming Language :: Python :: 3.12
Classifier: Programming Language :: Python :: Implementation :: CPython
Classifier: Programming Language :: Python :: Implementation :: PyPy
Classifier: Topic :: Scientific/Engineering
Classifier: Topic :: Scientific/Engineering :: Mathematics
Classifier: Topic :: Software Development :: Interpreters
License-File: LICENSE
Requires-Dist: Mathics3>=8.0.0
Requires-Dist: networkx>=3.0.0
Requires-Dist: pydot
Requires-Dist: matplotlib
Requires-Dist: scipy>=1.10.0
Dynamic: classifier
Dynamic: description
Dynamic: description-content-type
Dynamic: maintainer
Dynamic: maintainer-email
Dynamic: requires-dist
